LICENSE
MANIFEST.in
README.md
setup.py
云账户SDK-for-Python-pypi.md
yunzhanghu_sdk/__init__.py
yunzhanghu_sdk/config.py
yunzhanghu_sdk/message.py
yunzhanghu_sdk/utils.py
yunzhanghu_sdk.egg-info/PKG-INFO
yunzhanghu_sdk.egg-info/SOURCES.txt
yunzhanghu_sdk.egg-info/dependency_links.txt
yunzhanghu_sdk.egg-info/requires.txt
yunzhanghu_sdk.egg-info/top_level.txt
yunzhanghu_sdk/client/__init__.py
yunzhanghu_sdk/client/base.py
yunzhanghu_sdk/client/api/__init__.py
yunzhanghu_sdk/client/api/apiusersign_client.py
yunzhanghu_sdk/client/api/authentication_client.py
yunzhanghu_sdk/client/api/bizlicgxv2h5_client.py
yunzhanghu_sdk/client/api/bizlicgxv2h5api_client.py
yunzhanghu_sdk/client/api/bizlicxjjh5_client.py
yunzhanghu_sdk/client/api/bizlicxjjh5api_client.py
yunzhanghu_sdk/client/api/calculatelabor_client.py
yunzhanghu_sdk/client/api/custom_client.py
yunzhanghu_sdk/client/api/dataservice_client.py
yunzhanghu_sdk/client/api/h5usersign_client.py
yunzhanghu_sdk/client/api/invoice_client.py
yunzhanghu_sdk/client/api/payment_client.py
yunzhanghu_sdk/client/api/realname_client.py
yunzhanghu_sdk/client/api/tax_client.py
yunzhanghu_sdk/client/api/uploadusersign_client.py
yunzhanghu_sdk/client/api/usercollect_client.py
yunzhanghu_sdk/client/api/model/__init__.py
yunzhanghu_sdk/client/api/model/apiusersign.py
yunzhanghu_sdk/client/api/model/authentication.py
yunzhanghu_sdk/client/api/model/bizlicgxv2h5.py
yunzhanghu_sdk/client/api/model/bizlicgxv2h5api.py
yunzhanghu_sdk/client/api/model/bizlicxjjh5.py
yunzhanghu_sdk/client/api/model/bizlicxjjh5api.py
yunzhanghu_sdk/client/api/model/calculatelabor.py
yunzhanghu_sdk/client/api/model/dataservice.py
yunzhanghu_sdk/client/api/model/h5usersign.py
yunzhanghu_sdk/client/api/model/invoice.py
yunzhanghu_sdk/client/api/model/payment.py
yunzhanghu_sdk/client/api/model/realname.py
yunzhanghu_sdk/client/api/model/tax.py
yunzhanghu_sdk/client/api/model/uploadusersign.py
yunzhanghu_sdk/client/api/model/usercollect.py