Metadata-Version: 2.1
Name: yunzhanghu-sdk
Version: 1.0.28
Summary: 云账户官方 SDK for Python
Home-page: UNKNOWN
Author: yunzhanghu
License: UNKNOWN
Platform: UNKNOWN
Classifier: Programming Language :: Python :: 3
License-File: LICENSE
